dummy_massivekit-0.10.0.dist-info/licenses/LICENSE
mkit/api/__init__.py
mkit/api/dummy.py
mkit/core/__init__.py
dummy_massivekit-0.10.0.dist-info/METADATA
dummy_massivekit-0.10.0.dist-info/WHEEL
dummy_massivekit-0.10.0.dist-info/top_level.txt
dummy_massivekit-0.10.0.dist-info/RECORD
