Metadata-Version: 2.4
Name: dummy_massivekit
Version: 0.10.0
Summary: MassiveKit: Declarative framework for APIs, ETL and Microservices with Clean Code and SOLID principles
Author: MassiveDataScope
License: MIT
Keywords: fastapi,clean-architecture,solid,omegaconf
Requires-Python: >=3.11
License-File: LICENSE
Requires-Dist: pydantic>=2.8
Requires-Dist: omegaconf>=2.3
Requires-Dist: typing-extensions>=4.9
Requires-Dist: anyio>=4.4
Provides-Extra: api
Requires-Dist: fastapi>=0.115; extra == "api"
Requires-Dist: uvicorn[standard]>=0.30; extra == "api"
Requires-Dist: orjson>=3.10; extra == "api"
Requires-Dist: httpx>=0.27; extra == "api"
Requires-Dist: sqlalchemy>=2.0; extra == "api"
Requires-Dist: asyncpg>=0.29; extra == "api"
Requires-Dist: boto3>=1.34; extra == "api"
Dynamic: license-file
